cdk8s_redis_sts/__init__.py
cdk8s_redis_sts/py.typed
cdk8s_redis_sts/_jsii/__init__.py
cdk8s_redis_sts/_jsii/cdk8s-redis-sts@0.0.7.jsii.tgz
cdk8s_redis_sts-0.0.7.dist-info/METADATA
cdk8s_redis_sts-0.0.7.dist-info/WHEEL
cdk8s_redis_sts-0.0.7.dist-info/top_level.txt
cdk8s_redis_sts-0.0.7.dist-info/RECORD
