Metadata-Version: 2.1
Name: cdk8s-redis-sts
Version: 0.0.7
Summary: @opencdk8s/cdk8s-redis-sts
Home-page: https://github.com/opencdk8s/cdk8s-redis-sts
Author: Hunter Thompson<aatman@auroville.org.in>
License: Apache-2.0
Project-URL: Source, https://github.com/opencdk8s/cdk8s-redis-sts
Platform: UNKNOWN
Classifier: Intended Audience :: Developers
Classifier: Operating System :: OS Independent
Classifier: Programming Language :: JavaScript
Classifier: Programming Language :: Python :: 3 :: Only
Classifier: Programming Language :: Python :: 3.6
Classifier: Programming Language :: Python :: 3.7
Classifier: Programming Language :: Python :: 3.8
Classifier: Programming Language :: Python :: 3.9
Classifier: Typing :: Typed
Classifier: Development Status :: 4 - Beta
Classifier: License :: OSI Approved
Requires-Python: >=3.6
Requires-Dist: cdk8s-plus-17 (<2.0.0,>=1.0.0.b8)
Requires-Dist: cdk8s (<2.0.0,>=1.0.0.b8)
Requires-Dist: constructs (<4.0.0,>=3.3.5)
Requires-Dist: jsii (<2.0.0,>=1.20.1)
Requires-Dist: publication (>=0.0.3)
